setup.py
physplt/__init__.py
physplt.egg-info/PKG-INFO
physplt.egg-info/SOURCES.txt
physplt.egg-info/dependency_links.txt
physplt.egg-info/not-zip-safe
physplt.egg-info/requires.txt
physplt.egg-info/top_level.txt