Metadata-Version: 1.0
Name: physplt
Version: 0.1.0
Summary: A collection of functions to obscure the matplotlib code needed to plot standard physics graphs
Home-page: https://github.com/kaumaron/physplt
Author: Andrew DeCotiis-Mauro
Author-email: andrew.decotiis.mauro@gmail.com
License: GPL-3.0+
Platform: UNKNOWN
